rdxz2_utill-1.0.0.dist-info/licenses/LICENSE
utill/__init__.py
utill/my_bq.py
utill/my_const.py
utill/my_csv.py
utill/my_datetime.py
utill/my_dict.py
utill/my_encryption.py
utill/my_env.py
utill/my_file.py
utill/my_gcs.py
utill/my_input.py
utill/my_json.py
utill/my_mb.py
utill/my_pg.py
utill/my_queue.py
utill/my_string.py
utill/my_style.py
utill/my_tunnel.py
utill/my_xlsx.py
utill/cmd/__init__.py
utill/cmd/_bq.py
utill/cmd/_conf.py
utill/cmd/_enc.py
utill/cmd/_main.py
utill/cmd/_pg.py
utill/cmd/utill.py
rdxz2_utill-1.0.0.dist-info/METADATA
rdxz2_utill-1.0.0.dist-info/WHEEL
rdxz2_utill-1.0.0.dist-info/entry_points.txt
rdxz2_utill-1.0.0.dist-info/top_level.txt
rdxz2_utill-1.0.0.dist-info/RECORD
