Metadata-Version: 2.4
Name: rdxz2-utill
Version: 1.0.0
Summary: A small example package
Author-email: Richard Dharmawan <richard.dharmawan@gmail.com>
License: MIT License
Classifier: Programming Language :: Python :: 3
Classifier: Programming Language :: Python :: 3.12
Classifier: Programming Language :: Python :: 3 :: Only
Classifier: License :: OSI Approved :: MIT License
Classifier: Operating System :: OS Independent
Requires-Python: >=3.12
License-File: LICENSE
Requires-Dist: click==8.1.8
Requires-Dist: duckdb==1.1.3
Requires-Dist: humanize==4.11.0
Requires-Dist: loguru==0.7.3
Requires-Dist: paramiko==3.5.0
Requires-Dist: pydantic-settings==2.7.1
Requires-Dist: pydantic==2.10.6
Requires-Dist: requests==2.32.3
Requires-Dist: sshtunnel==0.4.0
Provides-Extra: google-cloud
Requires-Dist: google-cloud-bigquery==3.29.0; extra == "google-cloud"
Requires-Dist: google-cloud-storage==3.0.0; extra == "google-cloud"
Provides-Extra: postgresql
Requires-Dist: psycopg==3.2.2; extra == "postgresql"
Provides-Extra: pdf
Requires-Dist: PyPDF2==3.0.1; extra == "pdf"
Dynamic: license-file
